[
  {
    "osoba": "Dudusia i Rulek",
    "komentarz": "Pozdrawiamy z Leverkusen!! JR!",
    "kwota": "1000.0",
    "data": "2026-04-24T22:31:53.431000+02:00"
  },
  {
    "osoba": "Kamila",
    "komentarz": "Dokładam swoją cegiełkę dla dzieciaczków ! Wygracie walkę, trzymam kciuki z całego serduszka!",
    "kwota": "500.0",
    "data": "2026-04-26T02:35:04.075000+02:00"
  },
  {
    "osoba": "Ewa i Witold Grabowscy",
    "komentarz": "Piękna inicjatywa i skromny wspaniały człowiek. Dobro łączy.",
    "kwota": "500.0",
    "data": "2026-04-26T16:10:26.474000+02:00"
  },
  {
    "osoba": "Iza i Jarogniew",
    "komentarz": "Piękna sprawa ❤️",
    "kwota": "500.0",
    "data": "2026-04-25T12:14:14.568000+02:00"
  },
  {
    "osoba": "Vafu",
    "komentarz": "💪💪",
    "kwota": "500.0",
    "data": "2026-04-25T23:50:43.843000+02:00"
  },
  {
    "osoba": "Anonim",
    "komentarz": "Jazda!",
    "kwota": "500.0",
    "data": "2026-04-26T19:12:47.622000+02:00"
  },
  {
    "osoba": "OlaLenaLiliTomiJanek",
    "komentarz": "Love ❤️❤️❤️",
    "kwota": "500.0",
    "data": "2026-04-26T12:36:38.239000+02:00"
  },
  {
    "osoba": "Kubuś i Ania",
    "komentarz": "Jesteście wspaniali. Dobra robota. Polska gurom♥️",
    "kwota": "500.0",
    "data": "2026-04-26T19:23:56.117000+02:00"
  },
  {
    "osoba": "Adrian i Wioleta Byzia",
    "komentarz": "Super Inicjatywa , Sam Miałem Nowotwór i wiem co to jest , Cieszę Się , Że wyszła taka Akcja i życzę powodzenia ! Razem Możemy Więcej <3",
    "kwota": "500.0",
    "data": "2026-04-26T11:48:48.235000+02:00"
  },
  {
    "osoba": "Patryk",
    "komentarz": "Dziękujemy!",
    "kwota": "500.0",
    "data": "2026-04-24T22:47:32.633000+02:00"
  },
  {
    "osoba": "Stachu",
    "komentarz": "Śrubujemy śrubujemy! Łatwo, Bedi ***** szefy.",
    "kwota": "500.0",
    "data": "2026-04-26T19:15:49.366000+02:00"
  },
  {
    "osoba": "Piotr",
    "komentarz": "Super inicjatywa, lecimy!",
    "kwota": "250.0",
    "data": "2026-04-26T09:11:02.382000+02:00"
  },
  {
    "osoba": "Frano z woli XDD",
    "komentarz": "Pozdro Janooo",
    "kwota": "200.0",
    "data": "2026-04-26T04:12:03.379000+02:00"
  },
  {
    "osoba": "Ela UK",
    "komentarz": "Wspieramy z wielkiej Brytanii",
    "kwota": "200.0",
    "data": "2026-04-26T12:59:16.348324+02:00"
  },
  {
    "osoba": "Kbk!!",
    "komentarz": "Kbk Kbk Kbk Kbk",
    "kwota": "200.0",
    "data": "2026-04-26T20:26:57.682000+02:00"
  },
  {
    "osoba": "Anonim",
    "komentarz": "Walczymy !!!!!",
    "kwota": "200.0",
    "data": "2026-04-26T15:57:03.085000+02:00"
  },
  {
    "osoba": "Konrad Zieliński",
    "komentarz": "Jestesmy z wami, nie jest nam obojętna ta sytuacja",
    "kwota": "200.0",
    "data": "2026-04-26T16:07:10.625000+02:00"
  },
  {
    "osoba": "Kacperz",
    "komentarz": "💪💪💪",
    "kwota": "200.0",
    "data": "2026-04-26T13:57:17.228000+02:00"
  },
  {
    "osoba": "Ania",
    "komentarz": "👍💕",
    "kwota": "200.0",
    "data": "2026-04-25T20:47:46.444000+02:00"
  },
  {
    "osoba": "Darek",
    "komentarz": "Super inicjatywa",
    "kwota": "200.0",
    "data": "2026-04-26T15:08:03.056000+02:00"
  },
  {
    "osoba": "Bernaty",
    "komentarz": "JESTEŚMY Z WAMI!",
    "kwota": "200.0",
    "data": "2026-04-26T15:46:54.914000+02:00"
  },
  {
    "osoba": "Anonim",
    "komentarz": "Zdrówka",
    "kwota": "200.0",
    "data": "2026-04-25T15:57:34.987000+02:00"
  },
  {
    "osoba": "Aga",
    "komentarz": "To co robicie jest niesamowite!",
    "kwota": "200.0",
    "data": "2026-04-26T07:16:05.716000+02:00"
  },
  {
    "osoba": "Tomek",
    "komentarz": "Wytrwałości i szybkiego powrotu do zdrowia dla walczących z rakiem! ❤️",
    "kwota": "200.0",
    "data": "2026-04-26T21:04:28.650000+02:00"
  },
  {
    "osoba": "Dawid Janduła",
    "komentarz": "Dziękuję za wszystko co robicie <3",
    "kwota": "200.0",
    "data": "2026-04-26T19:36:04.864000+02:00"
  },
  {
    "osoba": "KULIO *WYN *",
    "komentarz": "Dla dzieciaków",
    "kwota": "200.0",
    "data": "2026-04-23T19:51:36.242000+02:00"
  },
  {
    "osoba": "Mateusz",
    "komentarz": "Ciśniemy dalej",
    "kwota": "200.0",
    "data": "2026-04-26T13:17:27.807000+02:00"
  },
  {
    "osoba": "Bea",
    "komentarz": "Rozwalanie system",
    "kwota": "200.0",
    "data": "2026-04-26T12:31:23.313000+02:00"
  },
  {
    "osoba": "Tadyszki",
    "komentarz": "🥰",
    "kwota": "200.0",
    "data": "2026-04-26T13:09:35.826000+02:00"
  },
  {
    "osoba": "PMEH",
    "komentarz": "100 TO ZA MAŁO !!!! 😄",
    "kwota": "200.0",
    "data": "2026-04-26T10:52:41.650000+02:00"
  },
  {
    "osoba": "FiLiP",
    "komentarz": "BRAWO BRAWO BRAWO BRAWO BRAWO BRAWO BRAWO",
    "kwota": "200.0",
    "data": "2026-04-26T21:29:39.591000+02:00"
  },
  {
    "osoba": "Szacunek",
    "komentarz": "Szacunek dla was",
    "kwota": "200.0",
    "data": "2026-04-26T08:03:39.838000+02:00"
  },
  {
    "osoba": "Blanka i Iga z rodzicami",
    "komentarz": "Jesteście wielcy!!",
    "kwota": "200.0",
    "data": "2026-04-26T13:54:17.217000+02:00"
  },
  {
    "osoba": "BEBE",
    "komentarz": "Karina kocham cię, a wy oby tak dalej",
    "kwota": "200.0",
    "data": "2026-04-24T20:14:29.442000+02:00"
  },
  {
    "osoba": "Anonim",
    "komentarz": "Wielki szacunek!",
    "kwota": "200.0",
    "data": "2026-04-25T23:18:25.756000+02:00"
  },
  {
    "osoba": "Reprezentanci Polaków w Belgi",
    "komentarz": "Pomagamy I wspieramy",
    "kwota": "200.0",
    "data": "2026-04-26T15:41:56.005000+02:00"
  },
  {
    "osoba": "M.F.",
    "komentarz": "Jesteście wspaniali!",
    "kwota": "200.0",
    "data": "2026-04-27T20:05:17.869000+02:00"
  },
  {
    "osoba": "Werka",
    "komentarz": "Jesteście wielcy ! Zdrówka dla wszystkich !",
    "kwota": "180.0",
    "data": "2026-04-26T13:50:59.696000+02:00"
  },
  {
    "osoba": "Ula",
    "komentarz": "Szczecin pozdrawia ❤️",
    "kwota": "150.0",
    "data": "2026-04-26T16:52:54.487000+02:00"
  },
  {
    "osoba": "Chromas",
    "komentarz": "PPV wrzosek vs szpilka",
    "kwota": "150.0",
    "data": "2026-04-25T13:27:56.037000+02:00"
  },
  {
    "osoba": "Od Wojtka i Jagody ❤️",
    "komentarz": "Dla małych i dużych wojowników! Jesteśmy z Wami",
    "kwota": "115.0",
    "data": "2026-04-26T20:21:53.196000+02:00"
  },
  {
    "osoba": "Olcia",
    "komentarz": "❤️❤️❤️",
    "kwota": "107.0",
    "data": "2026-04-26T11:45:11.073000+02:00"
  },
  {
    "osoba": "Anonim",
    "komentarz": "JR",
    "kwota": "100.0",
    "data": "2026-04-26T08:36:40.785000+02:00"
  },
  {
    "osoba": "Anonim",
    "komentarz": "Trzymajcie się!!❤️❤️",
    "kwota": "100.0",
    "data": "2026-04-26T17:54:04.786000+02:00"
  },
  {
    "osoba": "Kacper",
    "komentarz": "Tak trzymać chłopaki 💪 uk pozdrawiam",
    "kwota": "100.0",
    "data": "2026-04-26T20:17:48.924000+02:00"
  },
  {
    "osoba": "Anonim",
    "komentarz": "Tak trzymaj",
    "kwota": "100.0",
    "data": "2026-04-26T14:18:53.283000+02:00"
  },
  {
    "osoba": "Teresa",
    "komentarz": "!!!",
    "kwota": "100.0",
    "data": "2026-04-26T15:03:05.377000+02:00"
  },
  {
    "osoba": "SC",
    "komentarz": "Łatwogang świetna akcja! Dzieciaczki dużo siły!",
    "kwota": "100.0",
    "data": "2026-04-26T12:40:04.350000+02:00"
  },
  {
    "osoba": "Globi",
    "komentarz": "Super robota",
    "kwota": "100.0",
    "data": "2026-04-26T20:46:47.570000+02:00"
  },
  {
    "osoba": "Ada",
    "komentarz": "Dobijmy 200milionow!",
    "kwota": "100.0",
    "data": "2026-04-26T14:40:07.005000+02:00"
  },
  {
    "osoba": "MKZKM",
    "komentarz": "Dziękuję, że jesteście tak wspaniałymi ludźmi ❤️",
    "kwota": "100.0",
    "data": "2026-04-25T23:40:43.218000+02:00"
  },
  {
    "osoba": "Angela z Kalina",
    "komentarz": "Niech moc będzie z Wami dzieciaki",
    "kwota": "100.0",
    "data": "2026-04-26T19:13:11.057000+02:00"
  },
  {
    "osoba": "Maro",
    "komentarz": "Zdrówka i powodzenia!",
    "kwota": "100.0",
    "data": "2026-04-25T23:42:21.428000+02:00"
  },
  {
    "osoba": "Monika i Atrur",
    "komentarz": "Powodzenia ❤️❤️❤️❤️",
    "kwota": "100.0",
    "data": "2026-04-25T20:14:02.195000+02:00"
  },
  {
    "osoba": "Andrzej zaparty",
    "komentarz": "Pomagamy",
    "kwota": "100.0",
    "data": "2026-04-26T16:41:34.927000+02:00"
  },
  {
    "osoba": "David & Natalia",
    "komentarz": "Pięknie, powodzenia!",
    "kwota": "100.0",
    "data": "2026-04-25T09:41:33.131000+02:00"
  },
  {
    "osoba": "Buba z Oską",
    "komentarz": "Ogień Ogień!!!",
    "kwota": "100.0",
    "data": "2026-04-26T15:29:08.007000+02:00"
  },
  {
    "osoba": "Bartosz i Ola Szafrańscy",
    "komentarz": "JR",
    "kwota": "100.0",
    "data": "2026-04-25T19:14:24.641000+02:00"
  },
  {
    "osoba": "Kasia",
    "komentarz": "Super robota! Brawo!",
    "kwota": "100.0",
    "data": "2026-04-26T10:05:51.293000+02:00"
  },
  {
    "osoba": "agat widej",
    "komentarz": "JR",
    "kwota": "100.0",
    "data": "2026-04-26T16:12:03.523000+02:00"
  },
  {
    "osoba": "Kinga i Łukasz",
    "komentarz": "🫶",
    "kwota": "100.0",
    "data": "2026-04-26T17:46:42.145000+02:00"
  },
  {
    "osoba": "Bieszczadzki OffRoad",
    "komentarz": "🚖",
    "kwota": "100.0",
    "data": "2026-04-26T11:36:23.696000+02:00"
  },
  {
    "osoba": "Kilian",
    "komentarz": "❤️❤️❤️❤️❤️",
    "kwota": "100.0",
    "data": "2026-04-25T23:53:16.522000+02:00"
  },
  {
    "osoba": "Martyna",
    "komentarz": "<3",
    "kwota": "100.0",
    "data": "2026-04-25T13:58:38.633000+02:00"
  },
  {
    "osoba": "Gaciakbertówna",
    "komentarz": "Nie pozdrawiamy raka",
    "kwota": "100.0",
    "data": "2026-04-26T10:23:00.900000+02:00"
  },
  {
    "osoba": "Ania",
    "komentarz": "❣️",
    "kwota": "100.0",
    "data": "2026-04-28T13:23:17.238000+02:00"
  },
  {
    "osoba": "Misiusz",
    "komentarz": "Jazda!!!",
    "kwota": "100.0",
    "data": "2026-04-24T23:52:13.585000+02:00"
  },
  {
    "osoba": "Czaro",
    "komentarz": "Dobra robota 👍",
    "kwota": "100.0",
    "data": "2026-04-26T19:18:03.137000+02:00"
  },
  {
    "osoba": "Magda",
    "komentarz": "❤️❤️❤️",
    "kwota": "100.0",
    "data": "2026-04-25T17:48:28.975000+02:00"
  },
  {
    "osoba": "Anonim",
    "komentarz": "Mateuko",
    "kwota": "100.0",
    "data": "2026-04-26T14:38:31.110000+02:00"
  },
  {
    "osoba": "Anonim",
    "komentarz": "Dla dzieci ❤️",
    "kwota": "100.0",
    "data": "2026-04-25T06:56:55.518000+02:00"
  },
  {
    "osoba": "Asia",
    "komentarz": "Lubię Bedoesa 2115",
    "kwota": "100.0",
    "data": "2026-04-26T16:50:02.195000+02:00"
  },
  {
    "osoba": "Kasia ❤️ Wawrzynek",
    "komentarz": "Lecimy ❤️❤️❤️❤️❤️❤️❤️❤️",
    "kwota": "100.0",
    "data": "2026-04-26T09:49:39.704000+02:00"
  },
  {
    "osoba": "Adrian",
    "komentarz": "Brawo chłopaki",
    "kwota": "100.0",
    "data": "2026-04-26T19:38:16.008000+02:00"
  },
  {
    "osoba": "Aga",
    "komentarz": "Dla walczących z nie równym przeciwnikiem !",
    "kwota": "100.0",
    "data": "2026-04-24T21:38:22.216000+02:00"
  },
  {
    "osoba": "Michał M",
    "komentarz": "działajcie dalej",
    "kwota": "100.0",
    "data": "2026-04-26T15:31:59.784000+02:00"
  },
  {
    "osoba": "Grzegorz",
    "komentarz": "💪🏻💪🏻💪🏻",
    "kwota": "100.0",
    "data": "2026-04-26T12:54:57.682000+02:00"
  },
  {
    "osoba": "Paulina",
    "komentarz": "Będzie dobrze!",
    "kwota": "100.0",
    "data": "2026-04-26T17:33:06.096000+02:00"
  },
  {
    "osoba": "Michał✌️",
    "komentarz": "Yebać raka✌️ KOCHAM CIĘ MAMOO❤️",
    "kwota": "100.0",
    "data": "2026-04-26T15:10:35.280000+02:00"
  },
  {
    "osoba": "Julita",
    "komentarz": "pozdrooo",
    "kwota": "100.0",
    "data": "2026-04-27T21:52:25.477000+02:00"
  },
  {
    "osoba": "Karolina Bruśnicka",
    "komentarz": "Całym sercem z wami 😉",
    "kwota": "100.0",
    "data": "2026-04-26T17:56:24.214000+02:00"
  },
  {
    "osoba": "Ewa",
    "komentarz": "Bottrop Niemcy pozdrawiam!!!",
    "kwota": "100.0",
    "data": "2026-04-26T09:41:07.941000+02:00"
  },
  {
    "osoba": "Ania",
    "komentarz": "JR",
    "kwota": "100.0",
    "data": "2026-04-26T16:45:22.659000+02:00"
  },
  {
    "osoba": "Grzegorz",
    "komentarz": "Mega akcja!!",
    "kwota": "100.0",
    "data": "2026-04-26T18:52:24.343000+02:00"
  },
  {
    "osoba": "Filip OOL",
    "komentarz": "JR JR JR JR",
    "kwota": "100.0",
    "data": "2026-04-25T22:48:59.107000+02:00"
  },
  {
    "osoba": "Anonim",
    "komentarz": "Na zdrowie",
    "kwota": "100.0",
    "data": "2026-04-26T13:45:50.946000+02:00"
  },
  {
    "osoba": "Paweł i Kasia",
    "komentarz": "Wspieramy 🥰",
    "kwota": "100.0",
    "data": "2026-04-26T16:35:02.042000+02:00"
  },
  {
    "osoba": "Caro",
    "komentarz": "Mega szacun",
    "kwota": "100.0",
    "data": "2026-04-26T18:50:49.376000+02:00"
  },
  {
    "osoba": "Achtentommy",
    "komentarz": "JR",
    "kwota": "100.0",
    "data": "2026-04-26T10:30:20.681000+02:00"
  },
  {
    "osoba": "Gabrysia i Laurka",
    "komentarz": "My też wspieramy Walke z Rakiem",
    "kwota": "100.0",
    "data": "2026-04-26T10:57:06.065261+02:00"
  },
  {
    "osoba": "Michał z Katowic",
    "komentarz": "jesteście wspaniałymi ludźmi",
    "kwota": "100.0",
    "data": "2026-04-26T19:11:11.473000+02:00"
  },
  {
    "osoba": "Ola",
    "komentarz": "Wytrwałości i sily",
    "kwota": "100.0",
    "data": "2026-04-26T17:57:33.236000+02:00"
  },
  {
    "osoba": "Anonim",
    "komentarz": "Jesteście najsilniejsi na swiecie",
    "kwota": "100.0",
    "data": "2026-04-26T21:26:24.508000+02:00"
  },
  {
    "osoba": "KobylankaRecords",
    "komentarz": "Szpooooont",
    "kwota": "100.0",
    "data": "2026-04-26T12:04:57.396000+02:00"
  },
  {
    "osoba": "Danio i Andżelusia",
    "komentarz": "❤️❤️❤️",
    "kwota": "100.0",
    "data": "2026-04-23T18:57:54.475000+02:00"
  },
  {
    "osoba": "Marzenka i irek",
    "komentarz": "😄😄😄😄😄",
    "kwota": "100.0",
    "data": "2026-04-25T19:52:14.311000+02:00"
  },
  {
    "osoba": "Anonim",
    "komentarz": "❤️💓❤️💓👍",
    "kwota": "100.0",
    "data": "2026-04-26T21:20:25.399000+02:00"
  },
  {
    "osoba": "Paula",
    "komentarz": "Super inicjatywa 🥰",
    "kwota": "100.0",
    "data": "2026-04-25T19:03:21.387000+02:00"
  },
  {
    "osoba": "Anonim",
    "komentarz": "Ewelina",
    "kwota": "100.0",
    "data": "2026-04-26T16:39:06.879000+02:00"
  },
  {
    "osoba": "Anonim",
    "komentarz": "3majcie sie",
    "kwota": "100.0",
    "data": "2026-04-26T20:41:52.552000+02:00"
  },
  {
    "osoba": "Młotki",
    "komentarz": "Wspaniała robota!",
    "kwota": "100.0",
    "data": "2026-04-26T09:10:21.136000+02:00"
  },
  {
    "osoba": "Grzesiek",
    "komentarz": "Pozdro, Dobra Robota",
    "kwota": "100.0",
    "data": "2026-04-26T15:28:29.538000+02:00"
  },
  {
    "osoba": "Konstancja",
    "komentarz": "<3",
    "kwota": "100.0",
    "data": "2026-04-26T12:41:41.517000+02:00"
  },
  {
    "osoba": "Mariolka",
    "komentarz": "Pozdrawiam i powodzenia",
    "kwota": "100.0",
    "data": "2026-04-26T10:02:09.244000+02:00"
  },
  {
    "osoba": "Kuba i Wojtek",
    "komentarz": "Bijemy rekord !!!",
    "kwota": "87.0",
    "data": "2026-04-26T11:00:16.533000+02:00"
  },
  {
    "osoba": "JR!!!!!",
    "komentarz": "Kocham latwogenga",
    "kwota": "80.0",
    "data": "2026-04-26T11:16:24.410000+02:00"
  },
  {
    "osoba": "Iwo",
    "komentarz": "Petarda",
    "kwota": "80.0",
    "data": "2026-04-26T18:28:34.798000+02:00"
  },
  {
    "osoba": "Lena i Mechanik",
    "komentarz": "67",
    "kwota": "67.0",
    "data": "2026-04-25T21:21:10.689000+02:00"
  },
  {
    "osoba": "Rzepa",
    "komentarz": "JR",
    "kwota": "67.0",
    "data": "2026-04-26T21:07:49.474000+02:00"
  },
  {
    "osoba": "Kasia i Hania",
    "komentarz": "Cieszcie się życiem! Wysyłamy dużo miłości 😍",
    "kwota": "50.0",
    "data": "2026-04-25T23:32:17.733000+02:00"
  },
  {
    "osoba": "MMMSZ-y Zdw.",
    "komentarz": "Na zdrówko:)",
    "kwota": "50.0",
    "data": "2026-04-26T20:01:15.488000+02:00"
  },
  {
    "osoba": "Laurusia",
    "komentarz": "❤️❤️❤️❤️🥰",
    "kwota": "50.0",
    "data": "2026-04-25T19:49:20.372000+02:00"
  },
  {
    "osoba": "EveLine",
    "komentarz": "Pomagamy",
    "kwota": "50.0",
    "data": "2026-04-26T20:17:12.605289+02:00"
  },
  {
    "osoba": "Lilo , Tonia i Kuba",
    "komentarz": "<3",
    "kwota": "50.0",
    "data": "2026-04-25T22:06:54.881000+02:00"
  },
  {
    "osoba": "Kasia i Mateusz",
    "komentarz": "Wsparcie z Oławy !",
    "kwota": "50.0",
    "data": "2026-04-25T19:32:45.986000+02:00"
  },
  {
    "osoba": "Anonim",
    "komentarz": "❤️❤️",
    "kwota": "50.0",
    "data": "2026-04-26T13:33:09.600000+02:00"
  },
  {
    "osoba": "Marta",
    "komentarz": "Brawo! Jestem wzruszona!",
    "kwota": "50.0",
    "data": "2026-04-26T21:55:10.093000+02:00"
  },
  {
    "osoba": "Anonim",
    "komentarz": "Niech to się nie kończy <3",
    "kwota": "50.0",
    "data": "2026-04-26T20:26:06.843000+02:00"
  },
  {
    "osoba": "Jacek i Iwona Bonn",
    "komentarz": "Super Idee pozdrawiam",
    "kwota": "50.0",
    "data": "2026-04-26T17:10:58.634458+02:00"
  },
  {
    "osoba": "Iza",
    "komentarz": "♥️",
    "kwota": "50.0",
    "data": "2026-04-26T18:35:11.035000+02:00"
  },
  {
    "osoba": "Aneta Nowicka",
    "komentarz": "TRZYMAJCIE TAK DALEJ!!!!!!",
    "kwota": "50.0",
    "data": "2026-04-25T20:52:05.047000+02:00"
  },
  {
    "osoba": "Dominika H",
    "komentarz": "Kocham!",
    "kwota": "50.0",
    "data": "2026-04-26T10:45:18.632000+02:00"
  },
  {
    "osoba": "Anonim",
    "komentarz": "Lecimy po więcej ❤️",
    "kwota": "50.0",
    "data": "2026-04-26T13:36:30.907000+02:00"
  },
  {
    "osoba": "Anonim",
    "komentarz": "Dobro wraca 🤍",
    "kwota": "50.0",
    "data": "2026-04-26T15:56:53.782000+02:00"
  },
  {
    "osoba": "Amelka K.",
    "komentarz": "🥰🥰",
    "kwota": "50.0",
    "data": "2026-04-25T11:48:02.437000+02:00"
  },
  {
    "osoba": "Bronek",
    "komentarz": "OZK",
    "kwota": "50.0",
    "data": "2026-04-23T21:31:55.445000+02:00"
  },
  {
    "osoba": "Patryk",
    "komentarz": "Polska gurommm",
    "kwota": "50.0",
    "data": "2026-04-26T15:12:19.962000+02:00"
  },
  {
    "osoba": "Katarzyna Goss-Janicka",
    "komentarz": "Razem możemy więcej",
    "kwota": "50.0",
    "data": "2026-04-26T14:20:45.051000+02:00"
  },
  {
    "osoba": "Łukasz",
    "komentarz": "Dla małych wojowników",
    "kwota": "50.0",
    "data": "2026-04-26T15:47:08.564000+02:00"
  },
  {
    "osoba": "Elżunia",
    "komentarz": "🩷",
    "kwota": "50.0",
    "data": "2026-04-26T18:49:59.902000+02:00"
  },
  {
    "osoba": "Pepel",
    "komentarz": "Joł Joł nie powiem co",
    "kwota": "50.0",
    "data": "2026-04-25T16:43:54.198000+02:00"
  },
  {
    "osoba": "Filip",
    "komentarz": "Po 30 milionów",
    "kwota": "50.0",
    "data": "2026-04-24T22:07:11.697000+02:00"
  },
  {
    "osoba": "Ola",
    "komentarz": "🤍",
    "kwota": "50.0",
    "data": "2026-04-26T14:36:37.410000+02:00"
  },
  {
    "osoba": "Beata",
    "komentarz": "Jedziemy!!",
    "kwota": "50.0",
    "data": "2026-04-26T18:08:24.826000+02:00"
  },
  {
    "osoba": "Izabela",
    "komentarz": "Jestem dumny, że jestem Polakiem!❤️‍🩹",
    "kwota": "50.0",
    "data": "2026-04-25T23:15:15.075000+02:00"
  },
  {
    "osoba": "Waski",
    "komentarz": "Tak trzymać",
    "kwota": "50.0",
    "data": "2026-04-26T21:00:52.334000+02:00"
  },
  {
    "osoba": "Klaudia W",
    "komentarz": "JR 🦀 Jedziemy z tym! ♥️",
    "kwota": "50.0",
    "data": "2026-04-26T01:14:06.176000+02:00"
  },
  {
    "osoba": "Joanna Żaguń",
    "komentarz": "Całym sercem z Wami 🫶🫶🫶",
    "kwota": "50.0",
    "data": "2026-04-26T14:19:34.968000+02:00"
  },
  {
    "osoba": "Marta",
    "komentarz": "Lecimy po 50 baniek!!",
    "kwota": "50.0",
    "data": "2026-04-24T14:13:10.897000+02:00"
  },
  {
    "osoba": "Gosia",
    "komentarz": "JR",
    "kwota": "50.0",
    "data": "2026-04-25T23:31:11.194000+02:00"
  },
  {
    "osoba": "Vicek",
    "komentarz": "Fenomenalna robota. Wraca wiara w ludzi ❤️",
    "kwota": "50.0",
    "data": "2026-04-25T21:45:28.628000+02:00"
  },
  {
    "osoba": "eRPe",
    "komentarz": "Śrubujemy!!!❤️❤️❤️",
    "kwota": "50.0",
    "data": "2026-04-26T16:05:40.355000+02:00"
  },
  {
    "osoba": "Becia",
    "komentarz": "Warto pomagać !",
    "kwota": "50.0",
    "data": "2026-04-26T21:10:02.809000+02:00"
  },
  {
    "osoba": "Gaspar i Ania",
    "komentarz": "JR",
    "kwota": "50.0",
    "data": "2026-04-26T09:50:04.240000+02:00"
  },
  {
    "osoba": "eniu",
    "komentarz": "dokładam cegiełkę",
    "kwota": "50.0",
    "data": "2026-04-24T16:28:33.638000+02:00"
  },
  {
    "osoba": "Tymek",
    "komentarz": "Pomagajmy !",
    "kwota": "50.0",
    "data": "2026-04-26T19:26:11.242000+02:00"
  },
  {
    "osoba": "Didi",
    "komentarz": "Powodzenia!",
    "kwota": "50.0",
    "data": "2026-04-25T19:06:04.436000+02:00"
  },
  {
    "osoba": "R.K",
    "komentarz": "Walczymy!",
    "kwota": "50.0",
    "data": "2026-04-26T13:59:09.713000+02:00"
  },
  {
    "osoba": "Nadia",
    "komentarz": "❤️❤️❤️",
    "kwota": "50.0",
    "data": "2026-04-26T19:27:14.072000+02:00"
  },
  {
    "osoba": "Dgt",
    "komentarz": "Pozdro po 100mln",
    "kwota": "50.0",
    "data": "2026-04-25T22:00:47.112000+02:00"
  },
  {
    "osoba": "GZP",
    "komentarz": "Niech dobro rozsiewa się wszędzie!:)",
    "kwota": "50.0",
    "data": "2026-04-26T13:32:51.417000+02:00"
  },
  {
    "osoba": "Aneta",
    "komentarz": "Ściskam mocno!",
    "kwota": "50.0",
    "data": "2026-04-26T07:50:14.115000+02:00"
  },
  {
    "osoba": "Olka",
    "komentarz": "Jesteś super! Więcej takich ludzi.",
    "kwota": "50.0",
    "data": "2026-04-26T12:29:35.667000+02:00"
  },
  {
    "osoba": "Dmochowski",
    "komentarz": "JR",
    "kwota": "50.0",
    "data": "2026-04-26T16:30:01.480000+02:00"
  },
  {
    "osoba": "Dominika",
    "komentarz": "JR",
    "kwota": "50.0",
    "data": "2026-04-27T17:23:04.945000+02:00"
  },
  {
    "osoba": "Wojtek i Martyna 🖤🖤🖤",
    "komentarz": "100 pęknie !!!",
    "kwota": "50.0",
    "data": "2026-04-25T22:01:04.884000+02:00"
  },
  {
    "osoba": "Anonim",
    "komentarz": "Lecimyyyyyyyy!!!!!!!!",
    "kwota": "50.0",
    "data": "2026-04-24T20:48:12.998000+02:00"
  },
  {
    "osoba": "Łukasz",
    "komentarz": "Strzelajcie",
    "kwota": "50.0",
    "data": "2026-04-25T23:29:23.925000+02:00"
  },
  {
    "osoba": "Patrycja i Dawid",
    "komentarz": "❤️",
    "kwota": "50.0",
    "data": "2026-04-26T16:11:25.942000+02:00"
  },
  {
    "osoba": "Agnieszka M ❤️",
    "komentarz": "Jesteście niesamowici",
    "kwota": "50.0",
    "data": "2026-04-26T20:09:28.758000+02:00"
  },
  {
    "osoba": "Ala",
    "komentarz": "Dzieciaki, jesteście mega silne i odważne. Jesteśmy z Wami!",
    "kwota": "50.0",
    "data": "2026-04-24T21:55:58.967000+02:00"
  },
  {
    "osoba": "Paweł i Ania",
    "komentarz": "Dobra robota!!",
    "kwota": "50.0",
    "data": "2026-04-26T15:43:20.724000+02:00"
  },
  {
    "osoba": "Paula",
    "komentarz": "❤️",
    "kwota": "50.0",
    "data": "2026-04-26T11:39:01.584000+02:00"
  },
  {
    "osoba": "Gajusia wspiera",
    "komentarz": "Gajusia wspiera",
    "kwota": "50.0",
    "data": "2026-04-26T14:26:59.922000+02:00"
  },
  {
    "osoba": "JUZBUD",
    "komentarz": "Ogień z rakiem",
    "kwota": "50.0",
    "data": "2026-04-26T19:13:44.091000+02:00"
  },
  {
    "osoba": "Marta",
    "komentarz": "Niezwykła inicjatywa, brawo!",
    "kwota": "50.0",
    "data": "2026-04-27T08:15:29.513000+02:00"
  },
  {
    "osoba": "Claudia i Basia",
    "komentarz": "Dobra robota ❤️",
    "kwota": "50.0",
    "data": "2026-04-24T21:01:51.064000+02:00"
  },
  {
    "osoba": "Prezes",
    "komentarz": "Pozdro",
    "kwota": "50.0",
    "data": "2026-04-24T21:03:51.761000+02:00"
  },
  {
    "osoba": "Rad Ok",
    "komentarz": "Super akcja",
    "kwota": "50.0",
    "data": "2026-04-26T10:31:41.259000+02:00"
  },
  {
    "osoba": "Fifi the grind",
    "komentarz": "Jazda z tym",
    "kwota": "50.0",
    "data": "2026-04-26T16:09:53.196000+02:00"
  },
  {
    "osoba": "Kuba",
    "komentarz": "JR",
    "kwota": "50.0",
    "data": "2026-04-26T11:19:04.543000+02:00"
  },
  {
    "osoba": "Anonim",
    "komentarz": "🩷🩷🩷",
    "kwota": "50.0",
    "data": "2026-04-24T13:14:14.958000+02:00"
  },
  {
    "osoba": "Od Pani kelnerki",
    "komentarz": "Zamiast napiwku",
    "kwota": "50.0",
    "data": "2026-04-26T14:27:38.354000+02:00"
  },
  {
    "osoba": "Katarzynka",
    "komentarz": "❤️❤️❤️",
    "kwota": "50.0",
    "data": "2026-04-26T16:36:12.466000+02:00"
  },
  {
    "osoba": "Beata",
    "komentarz": "♥️♥️♥️",
    "kwota": "50.0",
    "data": "2026-04-27T06:25:22.860000+02:00"
  },
  {
    "osoba": "AniaPiotrekGrzes",
    "komentarz": "Walka",
    "kwota": "50.0",
    "data": "2026-04-26T21:25:46.530000+02:00"
  },
  {
    "osoba": "futura + gnativx",
    "komentarz": "w tym tempie to 50 mln pęknie ❤️",
    "kwota": "50.0",
    "data": "2026-04-24T18:40:34.921000+02:00"
  },
  {
    "osoba": "Joszu",
    "komentarz": "❤️🇵🇱❤️🇵🇱",
    "kwota": "50.0",
    "data": "2026-04-26T15:17:58.406000+02:00"
  },
  {
    "osoba": "Matias",
    "komentarz": "Wspieram  ❤️💪",
    "kwota": "50.0",
    "data": "2026-04-26T21:01:45.411000+02:00"
  },
  {
    "osoba": "Grzegorz",
    "komentarz": "Pozdrawiam",
    "kwota": "50.0",
    "data": "2026-04-26T11:31:17.086000+02:00"
  },
  {
    "osoba": "FUGI POK",
    "komentarz": "SATAIII",
    "kwota": "50.0",
    "data": "2026-04-26T12:22:13.324000+02:00"
  },
  {
    "osoba": "Monkey_tatuaze",
    "komentarz": "Też wspieram!!",
    "kwota": "50.0",
    "data": "2026-04-25T15:02:18.994000+02:00"
  },
  {
    "osoba": "Anonim",
    "komentarz": "Trzymajcie się",
    "kwota": "50.0",
    "data": "2026-04-26T20:23:14.937000+02:00"
  },
  {
    "osoba": "Ania",
    "komentarz": "❤️",
    "kwota": "50.0",
    "data": "2026-04-26T14:49:52.567000+02:00"
  },
  {
    "osoba": "Agatka lat 10",
    "komentarz": "Jestem z Wami:)",
    "kwota": "50.0",
    "data": "2026-04-26T13:55:36.199000+02:00"
  },
  {
    "osoba": "Wuczi",
    "komentarz": "Niech moc będzie z dzieciakami! ❤️",
    "kwota": "50.0",
    "data": "2026-04-26T13:33:13.275000+02:00"
  },
  {
    "osoba": "Milena",
    "komentarz": "Super akcja! Jesteście wielcy! Brawa dla wszystkich,którzy wpłacają i pomagają 👍🏼",
    "kwota": "50.0",
    "data": "2026-04-26T19:02:23.677000+02:00"
  },
  {
    "osoba": "Nati",
    "komentarz": "LET'S GOO",
    "kwota": "50.0",
    "data": "2026-04-24T22:28:49.605000+02:00"
  },
  {
    "osoba": "Marta",
    "komentarz": "Robicie świetną robotę!",
    "kwota": "50.0",
    "data": "2026-04-25T00:35:09.381000+02:00"
  },
  {
    "osoba": "Anna",
    "komentarz": "Ogień",
    "kwota": "50.0",
    "data": "2026-04-27T12:23:27.647000+02:00"
  },
  {
    "osoba": "Anonim",
    "komentarz": "JR",
    "kwota": "50.0",
    "data": "2026-04-24T13:57:53.700000+02:00"
  },
  {
    "osoba": "Dawid",
    "komentarz": "Dobry moment hehe",
    "kwota": "50.0",
    "data": "2026-04-24T23:31:41.973000+02:00"
  },
  {
    "osoba": "Paulina i Patryk",
    "komentarz": "Wspieramy całą rodziną",
    "kwota": "50.0",
    "data": "2026-04-24T13:56:17.856000+02:00"
  },
  {
    "osoba": "Magda i Mati",
    "komentarz": "Serce dla Was",
    "kwota": "50.0",
    "data": "2026-04-26T13:31:39.706000+02:00"
  },
  {
    "osoba": "Daniel",
    "komentarz": "JR",
    "kwota": "50.0",
    "data": "2026-04-26T10:17:23.312000+02:00"
  },
  {
    "osoba": "Alex",
    "komentarz": "💪🔥",
    "kwota": "50.0",
    "data": "2026-04-25T20:46:38.113000+02:00"
  },
  {
    "osoba": "Anonim",
    "komentarz": "Życzę  zdrowia, siły  walki i zwycięstwa",
    "kwota": "50.0",
    "data": "2026-04-26T18:53:12.679000+02:00"
  },
  {
    "osoba": "Anonim",
    "komentarz": "Każdy z nas walczy 🫶🏼",
    "kwota": "50.0",
    "data": "2026-04-26T15:44:42.446000+02:00"
  },
  {
    "osoba": "Remek",
    "komentarz": "Lecimyyyyyy",
    "kwota": "50.0",
    "data": "2026-04-26T21:26:45.120000+02:00"
  },
  {
    "osoba": "M i J",
    "komentarz": "👍👍👍❤️❤️❤️",
    "kwota": "50.0",
    "data": "2026-04-26T15:30:32.286000+02:00"
  },
  {
    "osoba": "Lidia",
    "komentarz": "Jestem razem z wami 🫶",
    "kwota": "50.0",
    "data": "2026-04-24T15:15:23.206000+02:00"
  },
  {
    "osoba": "Anonim",
    "komentarz": "Pomagamy",
    "kwota": "50.0",
    "data": "2026-04-26T21:05:39.200000+02:00"
  },
  {
    "osoba": "Ania",
    "komentarz": "Walczcie. Dobro wraca ❤️❤️❤️",
    "kwota": "50.0",
    "data": "2026-04-26T21:06:38.988000+02:00"
  },
  {
    "osoba": "hania",
    "komentarz": "!!!",
    "kwota": "50.0",
    "data": "2026-04-25T22:09:41.610000+02:00"
  },
  {
    "osoba": "Myncu",
    "komentarz": "Piękna sprawa!",
    "kwota": "50.0",
    "data": "2026-04-26T09:26:32.860000+02:00"
  },
  {
    "osoba": "Marta B",
    "komentarz": "Po raz kolejny dużo siły dla Dzieciaków i ukłony dla całej tej akcji!",
    "kwota": "50.0",
    "data": "2026-04-26T16:14:22.933000+02:00"
  },
  {
    "osoba": "Rodzinka Sidzinka",
    "komentarz": "Skawina pomaga",
    "kwota": "50.0",
    "data": "2026-04-25T22:22:59.331000+02:00"
  },
  {
    "osoba": "Kamil",
    "komentarz": "Dużo zdrowia Mali Bohaterowie",
    "kwota": "50.0",
    "data": "2026-04-26T12:43:27.972000+02:00"
  },
  {
    "osoba": "Luki Luluś i Izek",
    "komentarz": "Jebac raka",
    "kwota": "50.0",
    "data": "2026-04-26T15:28:37.268000+02:00"
  },
  {
    "osoba": "Mati ola",
    "komentarz": "Golimy",
    "kwota": "50.0",
    "data": "2026-04-24T11:30:03.724000+02:00"
  },
  {
    "osoba": "Małgorzata.K",
    "komentarz": "♥️",
    "kwota": "50.0",
    "data": "2026-04-26T20:20:22.001000+02:00"
  },
  {
    "osoba": "Moni",
    "komentarz": "Wspólnie damy radę ❤️👶🏼",
    "kwota": "47.0",
    "data": "2026-04-25T20:16:31.216000+02:00"
  },
  {
    "osoba": "Agatka🥰🥰",
    "komentarz": "Niech się darzy🥰🥰🥰",
    "kwota": "40.0",
    "data": "2026-04-26T17:24:35.780000+02:00"
  },
  {
    "osoba": "Kasia i Krzyś",
    "komentarz": "Je**ć raka!",
    "kwota": "40.0",
    "data": "2026-04-26T21:28:14.842000+02:00"
  },
  {
    "osoba": "Patka",
    "komentarz": "BUZIAKI DLA BOHATERÓW!!!",
    "kwota": "38.0",
    "data": "2026-04-26T00:22:03.829000+02:00"
  },
  {
    "osoba": "Angelika i Mateusz",
    "komentarz": "Łatwo jesteś wielki",
    "kwota": "37.0",
    "data": "2026-04-26T14:16:38.759000+02:00"
  },
  {
    "osoba": "Marysia i Alek lat7",
    "komentarz": "🤩🤩🤩🤩🤩🤩🤩🤩🤩🤩🤩🤩🤩🤩🤩🤩🤩🤩😍😍😍😍😍😍😍😍😍😍😍😍😍😍😌😍😌😌😌😌😍🤩🤩🤩🤩🤩🤩🙉🐵🤩🤩🤩🤩🤩🤩🤩🥳🥳🥳🥳",
    "kwota": "36.0",
    "data": "2026-04-26T12:06:21.133000+02:00"
  },
  {
    "osoba": "Gosia",
    "komentarz": "Super robota💪🏼💪🏼💪🏼",
    "kwota": "30.0",
    "data": "2026-04-26T12:50:55.031000+02:00"
  },
  {
    "osoba": "Oliwier Las",
    "komentarz": "Lecimy dalej",
    "kwota": "30.0",
    "data": "2026-04-26T09:06:21.961000+02:00"
  },
  {
    "osoba": "EdD",
    "komentarz": "Każdy może za chwilkę także potrzebować pomocy",
    "kwota": "30.0",
    "data": "2026-04-26T21:14:46.378000+02:00"
  },
  {
    "osoba": "Anonim",
    "komentarz": "Na zdrowie",
    "kwota": "30.0",
    "data": "2026-04-26T19:54:01.978000+02:00"
  },
  {
    "osoba": "Biwa",
    "komentarz": "JR!",
    "kwota": "30.0",
    "data": "2026-04-26T12:02:01.343000+02:00"
  },
  {
    "osoba": "Ania Lu",
    "komentarz": "❤️",
    "kwota": "30.0",
    "data": "2026-04-25T22:18:56.478000+02:00"
  },
  {
    "osoba": "Blizniaki",
    "komentarz": "Jesteście wspaniali",
    "kwota": "30.0",
    "data": "2026-04-26T12:06:38.945000+02:00"
  },
  {
    "osoba": "Miłosz",
    "komentarz": "Pozdrawiam JR",
    "kwota": "30.0",
    "data": "2026-04-26T20:58:11.433000+02:00"
  },
  {
    "osoba": "NB",
    "komentarz": "LECIMYYYYYY",
    "kwota": "27.51",
    "data": "2026-04-24T23:51:15.721000+02:00"
  },
  {
    "osoba": "Anonim",
    "komentarz": "Lecimy Jeszcze więcej!!!!!",
    "kwota": "25.0",
    "data": "2026-04-26T11:38:59.703000+02:00"
  },
  {
    "osoba": "Anonim",
    "komentarz": "💗",
    "kwota": "25.0",
    "data": "2026-04-26T21:29:57.660000+02:00"
  },
  {
    "osoba": "Kacpos",
    "komentarz": "Jr",
    "kwota": "21.37",
    "data": "2026-04-26T21:03:59.365000+02:00"
  },
  {
    "osoba": "Mikołaj woznaik",
    "komentarz": "Pozdro",
    "kwota": "21.37",
    "data": "2026-04-26T07:55:40.079000+02:00"
  },
  {
    "osoba": "Kasia",
    "komentarz": "Lecimy po 100 milionów!",
    "kwota": "20.0",
    "data": "2026-04-25T19:28:43.078000+02:00"
  },
  {
    "osoba": "Tata Frania",
    "komentarz": "Dla małych Muminków",
    "kwota": "20.0",
    "data": "2026-04-26T15:58:56.596000+02:00"
  },
  {
    "osoba": "Karolina i Grzegorz",
    "komentarz": "Wspieramy Dzieci Chorych Na Raka",
    "kwota": "20.0",
    "data": "2026-04-26T19:26:14.219000+02:00"
  },
  {
    "osoba": "Anonim",
    "komentarz": "Wysyłam dużo siły, wsparcia i dobrych myśli. Jesteście prawdziwymi wojownikami ❤️",
    "kwota": "20.0",
    "data": "2026-04-26T22:09:43.123000+02:00"
  },
  {
    "osoba": "Młoda",
    "komentarz": "JR!!!!",
    "kwota": "20.0",
    "data": "2026-04-26T22:47:07.401000+02:00"
  },
  {
    "osoba": "ww",
    "komentarz": "❤️❤️❤️",
    "kwota": "20.0",
    "data": "2026-04-26T10:06:07.494000+02:00"
  },
  {
    "osoba": "Klaudix",
    "komentarz": "Lecimyyyy",
    "kwota": "20.0",
    "data": "2026-04-25T23:13:55.346000+02:00"
  },
  {
    "osoba": "Sławek wicher",
    "komentarz": "Nie poddawajcie się",
    "kwota": "20.0",
    "data": "2026-04-26T17:43:37.108000+02:00"
  },
  {
    "osoba": "Anonim",
    "komentarz": "ZDRÓWKA I POMYŚLNOŚCI 💚😎",
    "kwota": "20.0",
    "data": "2026-04-26T08:43:49.761000+02:00"
  },
  {
    "osoba": "Ania",
    "komentarz": "Lecimyy",
    "kwota": "20.0",
    "data": "2026-04-24T22:04:59.393000+02:00"
  },
  {
    "osoba": "X",
    "komentarz": "Lecimy dalej, kochani!",
    "kwota": "20.0",
    "data": "2026-04-27T22:49:45.696000+02:00"
  },
  {
    "osoba": "Lazanczyk",
    "komentarz": "JR",
    "kwota": "20.0",
    "data": "2026-04-25T12:31:51.956000+02:00"
  },
  {
    "osoba": "Marta",
    "komentarz": "Go fighters!",
    "kwota": "20.0",
    "data": "2026-04-25T21:28:44.597000+02:00"
  },
  {
    "osoba": "Anonim",
    "komentarz": "Jesteście wielcy! :)",
    "kwota": "20.0",
    "data": "2026-04-26T13:32:13.614000+02:00"
  },
  {
    "osoba": "Miłoszek",
    "komentarz": "Pozdrawiam wszystkich wspierających",
    "kwota": "20.0",
    "data": "2026-04-26T15:07:56.161000+02:00"
  },
  {
    "osoba": "Anonim",
    "komentarz": "Gratulacje za świetny pomysł",
    "kwota": "20.0",
    "data": "2026-04-26T14:43:15.885000+02:00"
  },
  {
    "osoba": "Anonim",
    "komentarz": "Jesteście szaleni",
    "kwota": "20.0",
    "data": "2026-04-26T11:07:07.360000+02:00"
  },
  {
    "osoba": "Alicja",
    "komentarz": "Jesteście cudowni!!!",
    "kwota": "20.0",
    "data": "2026-04-26T10:26:04.822000+02:00"
  },
  {
    "osoba": "MR",
    "komentarz": "Super akcja",
    "kwota": "20.0",
    "data": "2026-04-24T22:27:14.404000+02:00"
  },
  {
    "osoba": "Szacunek!",
    "komentarz": "Walczymy",
    "kwota": "20.0",
    "data": "2026-04-26T09:31:00.878000+02:00"
  },
  {
    "osoba": "Adrian",
    "komentarz": "Pozdrawiam",
    "kwota": "20.0",
    "data": "2026-04-26T21:37:37.798000+02:00"
  },
  {
    "osoba": "Zawadzinscy",
    "komentarz": "Powodzenia pobijecie WOŚP !!",
    "kwota": "20.0",
    "data": "2026-04-26T17:10:37.657000+02:00"
  },
  {
    "osoba": "Roksana",
    "komentarz": "Piękna akcja!",
    "kwota": "20.0",
    "data": "2026-04-26T14:48:15.411000+02:00"
  },
  {
    "osoba": "Ten.lysy",
    "komentarz": "Wielkie pozdro",
    "kwota": "20.0",
    "data": "2026-04-25T21:56:01.746000+02:00"
  },
  {
    "osoba": "Amelka",
    "komentarz": "💜",
    "kwota": "20.0",
    "data": "2026-04-26T11:11:35.261000+02:00"
  },
  {
    "osoba": "Gosik",
    "komentarz": "Niech Wiktor zaśpiewa ,Tam słońce gdzie my,",
    "kwota": "20.0",
    "data": "2026-04-26T16:02:34.581000+02:00"
  },
  {
    "osoba": "Ewa",
    "komentarz": "Wszyscy potrzebujemy wspólnoty!",
    "kwota": "20.0",
    "data": "2026-04-26T10:15:37.326000+02:00"
  },
  {
    "osoba": "Filip k",
    "komentarz": "Dobra robota",
    "kwota": "20.0",
    "data": "2026-04-25T21:53:34.736000+02:00"
  },
  {
    "osoba": "Hania",
    "komentarz": "Najlepsi",
    "kwota": "20.0",
    "data": "2026-04-25T17:12:07.967000+02:00"
  },
  {
    "osoba": "Landziku",
    "komentarz": "Pozdrawiam <3",
    "kwota": "20.0",
    "data": "2026-04-25T16:15:59.156000+02:00"
  },
  {
    "osoba": "Molly",
    "komentarz": "Róbcie dalej dobro!",
    "kwota": "20.0",
    "data": "2026-04-26T17:21:14.778000+02:00"
  },
  {
    "osoba": "Victoria",
    "komentarz": "JR",
    "kwota": "20.0",
    "data": "2026-04-25T12:40:37.519000+02:00"
  },
  {
    "osoba": "Aga",
    "komentarz": ";)",
    "kwota": "20.0",
    "data": "2026-04-24T21:08:48.470000+02:00"
  },
  {
    "osoba": "Sonik",
    "komentarz": "jesteście najlepsi",
    "kwota": "20.0",
    "data": "2026-04-26T15:29:42.731000+02:00"
  },
  {
    "osoba": "Aggie & JD",
    "komentarz": "🏏🦀",
    "kwota": "20.0",
    "data": "2026-04-26T18:00:09.261000+02:00"
  },
  {
    "osoba": "Nesix",
    "komentarz": "❤️",
    "kwota": "20.0",
    "data": "2026-04-24T20:48:28.315000+02:00"
  },
  {
    "osoba": "Haniula i Kajunia",
    "komentarz": "Dajesz te pompeczki bedi",
    "kwota": "20.0",
    "data": "2026-04-26T16:38:28.799000+02:00"
  },
  {
    "osoba": "Anka",
    "komentarz": "Cudne rzeczy się dzieją ♥️",
    "kwota": "20.0",
    "data": "2026-04-26T13:24:59.648000+02:00"
  },
  {
    "osoba": "Anonim",
    "komentarz": "❤️",
    "kwota": "20.0",
    "data": "2026-04-26T11:55:46.408000+02:00"
  },
  {
    "osoba": "Ciocia",
    "komentarz": "Raku sio, sio!",
    "kwota": "20.0",
    "data": "2026-04-25T18:28:33.494000+02:00"
  },
  {
    "osoba": "Janek C",
    "komentarz": "Trzymajcie się",
    "kwota": "20.0",
    "data": "2026-04-26T19:18:02.980000+02:00"
  },
  {
    "osoba": "Indianiner:)",
    "komentarz": "Jedziemy!!!",
    "kwota": "20.0",
    "data": "2026-04-26T19:14:30.431000+02:00"
  },
  {
    "osoba": "Rodzinka",
    "komentarz": "Wielki szacun łatwo za ta akcje",
    "kwota": "20.0",
    "data": "2026-04-26T11:17:39.591000+02:00"
  },
  {
    "osoba": "wika",
    "komentarz": "lecimy 💪",
    "kwota": "20.0",
    "data": "2026-04-24T22:29:53.837000+02:00"
  },
  {
    "osoba": "Wojcieszeq",
    "komentarz": "❤️‍🔥❤️‍🔥❤️‍🔥",
    "kwota": "20.0",
    "data": "2026-04-24T10:03:32.697000+02:00"
  },
  {
    "osoba": "Teresa Jastrzębska",
    "komentarz": "Renia",
    "kwota": "20.0",
    "data": "2026-04-26T11:05:19.941000+02:00"
  },
  {
    "osoba": "Anonim",
    "komentarz": "Szacun",
    "kwota": "20.0",
    "data": "2026-04-26T20:00:44.799000+02:00"
  },
  {
    "osoba": "Konrad",
    "komentarz": "Naprzód!",
    "kwota": "20.0",
    "data": "2026-04-25T20:36:05.382000+02:00"
  },
  {
    "osoba": "Miki",
    "komentarz": "Dobro wraca!!!",
    "kwota": "20.0",
    "data": "2026-04-23T17:51:24.842000+02:00"
  },
  {
    "osoba": "Bodzionka",
    "komentarz": "JR",
    "kwota": "20.0",
    "data": "2026-04-26T19:05:07.587000+02:00"
  },
  {
    "osoba": "Anonim",
    "komentarz": "Nigdy się nie poddawajcie!",
    "kwota": "20.0",
    "data": "2026-04-24T17:10:43.395000+02:00"
  },
  {
    "osoba": "Anonim",
    "komentarz": "❤️",
    "kwota": "20.0",
    "data": "2026-04-26T18:35:00.071000+02:00"
  },
  {
    "osoba": "Kondziu",
    "komentarz": "Wołajcie Kielce!",
    "kwota": "20.0",
    "data": "2026-04-24T14:46:50.319000+02:00"
  },
  {
    "osoba": "Monika",
    "komentarz": "Dla dzieci",
    "kwota": "20.0",
    "data": "2026-04-28T21:15:48.176000+02:00"
  },
  {
    "osoba": "Oliwka",
    "komentarz": "❤️❤️",
    "kwota": "20.0",
    "data": "2026-04-26T20:00:03.841000+02:00"
  },
  {
    "osoba": "Zuzia",
    "komentarz": "JR",
    "kwota": "20.0",
    "data": "2026-04-26T20:36:02.000000+02:00"
  },
  {
    "osoba": "Madzia",
    "komentarz": "Zdrówka!",
    "kwota": "20.0",
    "data": "2026-04-25T10:51:48.399000+02:00"
  },
  {
    "osoba": "Julia💋",
    "komentarz": "JR!!!!!",
    "kwota": "20.0",
    "data": "2026-04-25T18:01:04.531000+02:00"
  },
  {
    "osoba": "Magdusia",
    "komentarz": "Super robota!",
    "kwota": "20.0",
    "data": "2026-04-25T22:46:54.495000+02:00"
  },
  {
    "osoba": "Marcin",
    "komentarz": "Piękna akcja",
    "kwota": "20.0",
    "data": "2026-04-26T12:18:15.286000+02:00"
  },
  {
    "osoba": "Kama",
    "komentarz": "Dużo siły",
    "kwota": "20.0",
    "data": "2026-04-26T11:00:08.751000+02:00"
  },
  {
    "osoba": "Pipolot",
    "komentarz": "JR",
    "kwota": "20.0",
    "data": "2026-04-25T20:11:38.343000+02:00"
  },
  {
    "osoba": "Szymon",
    "komentarz": "JR",
    "kwota": "20.0",
    "data": "2026-04-26T13:59:37.345000+02:00"
  },
  {
    "osoba": "Ewka",
    "komentarz": "POZDRO SZPAKU!🖤",
    "kwota": "20.0",
    "data": "2026-04-24T19:28:46.431000+02:00"
  },
  {
    "osoba": "Borys",
    "komentarz": "POZDRO WEJHEROWO! ;) powodzenia !",
    "kwota": "20.0",
    "data": "2026-04-26T11:27:31.281000+02:00"
  },
  {
    "osoba": "Lajk",
    "komentarz": "Dacie radę pokonać raka",
    "kwota": "20.0",
    "data": "2026-04-26T21:13:51.837000+02:00"
  },
  {
    "osoba": "Trebuh",
    "komentarz": "Super akcja!",
    "kwota": "20.0",
    "data": "2026-04-26T10:21:16.742000+02:00"
  },
  {
    "osoba": "Anonim",
    "komentarz": "Całym serduszkiem dla dzieci ❤️",
    "kwota": "20.0",
    "data": "2026-04-26T17:18:15.414000+02:00"
  },
  {
    "osoba": "Tytan",
    "komentarz": "Tytan ❤️",
    "kwota": "20.0",
    "data": "2026-04-26T08:48:15.838000+02:00"
  },
  {
    "osoba": "Michalina",
    "komentarz": "Jestescie wielcy",
    "kwota": "20.0",
    "data": "2026-04-25T21:11:31.714000+02:00"
  },
  {
    "osoba": "Anonim",
    "komentarz": "😍",
    "kwota": "20.0",
    "data": "2026-04-26T16:56:44.841000+02:00"
  },
  {
    "osoba": "Edyta - Edzia",
    "komentarz": "Z ogromnym podziękowaniem za całą akcję dla wszystkich.",
    "kwota": "20.0",
    "data": "2026-04-25T22:24:52.489000+02:00"
  },
  {
    "osoba": "Asia",
    "komentarz": "Kasix jestes super!",
    "kwota": "20.0",
    "data": "2026-04-24T11:31:52.700000+02:00"
  },
  {
    "osoba": "Ada",
    "komentarz": "Wszyscy razem",
    "kwota": "20.0",
    "data": "2026-04-26T12:21:50.064000+02:00"
  },
  {
    "osoba": "Anonim",
    "komentarz": "letss goo",
    "kwota": "20.0",
    "data": "2026-04-24T22:14:52.306000+02:00"
  },
  {
    "osoba": "Anonim",
    "komentarz": "Walczcie dzieciaki!!",
    "kwota": "20.0",
    "data": "2026-04-26T21:32:49.576000+02:00"
  },
  {
    "osoba": "Puszki zawsze razem",
    "komentarz": "Puszki zawsze razem",
    "kwota": "20.0",
    "data": "2026-04-25T23:05:53.438000+02:00"
  },
  {
    "osoba": "Martynka",
    "komentarz": "jazda gwiazda<33",
    "kwota": "20.0",
    "data": "2026-04-26T15:09:07.930000+02:00"
  },
  {
    "osoba": "Anonim",
    "komentarz": "💕",
    "kwota": "20.0",
    "data": "2026-04-24T22:27:27.576000+02:00"
  },
  {
    "osoba": "Aneta",
    "komentarz": ":)",
    "kwota": "20.0",
    "data": "2026-04-26T18:52:42.546000+02:00"
  },
  {
    "osoba": "Janek",
    "komentarz": "Pozdrawiamy Lublina",
    "kwota": "20.0",
    "data": "2026-04-26T15:56:39.260000+02:00"
  },
  {
    "osoba": "Zula",
    "komentarz": "JR",
    "kwota": "20.0",
    "data": "2026-04-26T16:33:07.990000+02:00"
  },
  {
    "osoba": "Ziółek",
    "komentarz": "OneTap ***** Rak",
    "kwota": "20.0",
    "data": "2026-04-24T21:23:46.984000+02:00"
  },
  {
    "osoba": "Kropka",
    "komentarz": "💪💪",
    "kwota": "20.0",
    "data": "2026-04-24T22:11:08.440000+02:00"
  },
  {
    "osoba": "Sandra",
    "komentarz": "Damy radę 🔥",
    "kwota": "20.0",
    "data": "2026-04-28T17:31:47.913000+02:00"
  },
  {
    "osoba": "Kinga",
    "komentarz": "❤️❤️❤️❤️",
    "kwota": "20.0",
    "data": "2026-04-26T14:08:51.755000+02:00"
  },
  {
    "osoba": "Ania",
    "komentarz": "🤞🤞",
    "kwota": "20.0",
    "data": "2026-04-25T15:08:14.353000+02:00"
  },
  {
    "osoba": "Zajo",
    "komentarz": "❤️",
    "kwota": "20.0",
    "data": "2026-04-25T14:58:11.192000+02:00"
  },
  {
    "osoba": "SylwekxBOR",
    "komentarz": "Tede x Peja",
    "kwota": "20.0",
    "data": "2026-04-26T15:51:59.375000+02:00"
  },
  {
    "osoba": "Kop3rr",
    "komentarz": "JR",
    "kwota": "20.0",
    "data": "2026-04-25T15:11:51.915000+02:00"
  },
  {
    "osoba": "Herman",
    "komentarz": "Paryż na swą wieżę kościoły ma lwów żadne miasto nie ma tego co ma wasilków",
    "kwota": "20.0",
    "data": "2026-04-25T22:41:30.578000+02:00"
  },
  {
    "osoba": "Monia",
    "komentarz": "Szacun,",
    "kwota": "20.0",
    "data": "2026-04-26T19:17:05.524000+02:00"
  },
  {
    "osoba": "Ola i Kamil",
    "komentarz": "Dajecie czadu!",
    "kwota": "20.0",
    "data": "2026-04-26T09:08:03.420000+02:00"
  },
  {
    "osoba": "Łukasz",
    "komentarz": "Mega robota",
    "kwota": "20.0",
    "data": "2026-04-24T23:00:37.083000+02:00"
  },
  {
    "osoba": "Maks",
    "komentarz": "jazda JR",
    "kwota": "20.0",
    "data": "2026-04-23T20:54:06.787000+02:00"
  },
  {
    "osoba": "Szymon",
    "komentarz": "NIGDY SIĘ NIE PODDAWAJCIE!!!",
    "kwota": "20.0",
    "data": "2026-04-24T23:09:52.764000+02:00"
  },
  {
    "osoba": "Rafał",
    "komentarz": "Zjednoczeni razem, damy rade",
    "kwota": "20.0",
    "data": "2026-04-26T19:00:10.552000+02:00"
  },
  {
    "osoba": "Anonim",
    "komentarz": "Kowanetz",
    "kwota": "20.0",
    "data": "2026-04-26T19:44:12.899000+02:00"
  },
  {
    "osoba": "Monia i Szymon",
    "komentarz": "Udało się!",
    "kwota": "20.0",
    "data": "2026-04-26T21:42:06.940000+02:00"
  },
  {
    "osoba": "Anonim",
    "komentarz": "❤️❤️❤️",
    "kwota": "20.0",
    "data": "2026-04-26T13:36:51.810000+02:00"
  },
  {
    "osoba": "Michał F",
    "komentarz": "Lecimy Kochani ;)",
    "kwota": "20.0",
    "data": "2026-04-26T09:55:35.812000+02:00"
  },
  {
    "osoba": "Aga",
    "komentarz": "Piotrek jesteś Wielki",
    "kwota": "20.0",
    "data": "2026-04-26T11:22:28.049000+02:00"
  },
  {
    "osoba": "Anonim",
    "komentarz": "Pozdrowienia z Wronek",
    "kwota": "20.0",
    "data": "2026-04-26T15:30:05.099000+02:00"
  },
  {
    "osoba": "Adrian",
    "komentarz": "JR",
    "kwota": "20.0",
    "data": "2026-04-26T16:09:12.534000+02:00"
  },
  {
    "osoba": "Lucas",
    "komentarz": "Lecimy!!!!",
    "kwota": "20.0",
    "data": "2026-04-26T14:03:28.945000+02:00"
  },
  {
    "osoba": "Emilka i Rafał",
    "komentarz": "Dla Dzieciaczków 🥺❤️",
    "kwota": "20.0",
    "data": "2026-04-26T19:33:46.408000+02:00"
  },
  {
    "osoba": "Pomagamy",
    "komentarz": "Nie poddawajcie się",
    "kwota": "20.0",
    "data": "2026-04-25T18:48:49.094000+02:00"
  },
  {
    "osoba": "Monika",
    "komentarz": "🩷🩷🩷🩷🩷🩷🩷🩷",
    "kwota": "19.31",
    "data": "2026-04-26T15:56:42.367000+02:00"
  },
  {
    "osoba": "Danka",
    "komentarz": "Wspieram",
    "kwota": "17.0",
    "data": "2026-04-24T21:12:03.152000+02:00"
  },
  {
    "osoba": "Karo polska",
    "komentarz": "Wspieramy nie ziewamy 🥱",
    "kwota": "16.7",
    "data": "2026-04-24T09:59:53.891000+02:00"
  },
  {
    "osoba": "Roguszeq",
    "komentarz": "Dacie radę super robota !!!",
    "kwota": "15.0",
    "data": "2026-04-26T19:14:40.750000+02:00"
  },
  {
    "osoba": "Anonim",
    "komentarz": "❤️",
    "kwota": "15.0",
    "data": "2026-04-24T23:40:19.086000+02:00"
  },
  {
    "osoba": "Natalia",
    "komentarz": "Czekam na wynik 9 liczbowy ❤️",
    "kwota": "15.0",
    "data": "2026-04-25T20:12:22.564000+02:00"
  },
  {
    "osoba": "Lila",
    "komentarz": "💗💗💗",
    "kwota": "15.0",
    "data": "2026-04-25T20:40:16.684000+02:00"
  },
  {
    "osoba": "Angelika Ka",
    "komentarz": "Płaczę przez was. Szacun",
    "kwota": "15.0",
    "data": "2026-04-24T01:55:24.690000+02:00"
  },
  {
    "osoba": "Bartek_P",
    "komentarz": "Zmieniamy świat na lepsze ❤️",
    "kwota": "15.0",
    "data": "2026-04-26T17:44:12.871000+02:00"
  },
  {
    "osoba": "Zuzia Jaroniec",
    "komentarz": "jestem z wami❤️",
    "kwota": "15.0",
    "data": "2026-04-26T21:57:15.272000+02:00"
  },
  {
    "osoba": "Justynkaa",
    "komentarz": "POMAGAMY!!!",
    "kwota": "15.0",
    "data": "2026-04-26T11:06:56.899000+02:00"
  },
  {
    "osoba": "Joanna",
    "komentarz": "Jestem z Wami",
    "kwota": "15.0",
    "data": "2026-04-26T20:54:39.350000+02:00"
  },
  {
    "osoba": "Krzysztof i Maria",
    "komentarz": "Z moreny",
    "kwota": "14.0",
    "data": "2026-04-26T14:18:37.730000+02:00"
  },
  {
    "osoba": "angela",
    "komentarz": "🥰🥰🥰",
    "kwota": "13.13",
    "data": "2026-04-25T22:53:05.166000+02:00"
  },
  {
    "osoba": "Angelika Knach",
    "komentarz": "🤍💙💛",
    "kwota": "12.0",
    "data": "2026-04-26T16:09:41.530000+02:00"
  },
  {
    "osoba": "Anonim",
    "komentarz": "Jesteście wspaniali!",
    "kwota": "10.0",
    "data": "2026-04-26T23:14:00.422000+02:00"
  },
  {
    "osoba": "❤️❤️❤️❤️",
    "komentarz": "POMAGAM BO MOGĘ",
    "kwota": "10.0",
    "data": "2026-04-26T17:37:03.108000+02:00"
  },
  {
    "osoba": "Juliaaa",
    "komentarz": "Piękna akcja JR",
    "kwota": "10.0",
    "data": "2026-04-24T20:03:43.658000+02:00"
  },
  {
    "osoba": "Ludwik",
    "komentarz": "Lets go",
    "kwota": "10.0",
    "data": "2026-04-26T10:44:02.332000+02:00"
  },
  {
    "osoba": "Anonim",
    "komentarz": "Moze nie dużo ale zawsze cos",
    "kwota": "10.0",
    "data": "2026-04-26T11:41:52.147000+02:00"
  },
  {
    "osoba": "Christoforos",
    "komentarz": "Jazda z rakiem",
    "kwota": "10.0",
    "data": "2026-04-25T21:22:06.015000+02:00"
  },
  {
    "osoba": "Anonim",
    "komentarz": "})i({",
    "kwota": "10.0",
    "data": "2026-04-26T19:16:46.468000+02:00"
  },
  {
    "osoba": "Lesia",
    "komentarz": "❤️❤️❤️",
    "kwota": "10.0",
    "data": "2026-04-23T16:49:19.604000+02:00"
  },
  {
    "osoba": "Tom",
    "komentarz": "Tak trzymać!!!",
    "kwota": "10.0",
    "data": "2026-04-24T14:47:36.753000+02:00"
  },
  {
    "osoba": "Łukasz",
    "komentarz": "JR JR",
    "kwota": "10.0",
    "data": "2026-04-25T08:26:42.911000+02:00"
  },
  {
    "osoba": "Marta",
    "komentarz": "Wspaniała inicjatywa!",
    "kwota": "10.0",
    "data": "2026-04-24T20:44:32.117000+02:00"
  },
  {
    "osoba": "kazik",
    "komentarz": "Goooo!",
    "kwota": "10.0",
    "data": "2026-04-26T20:45:09.494000+02:00"
  },
  {
    "osoba": "Dk",
    "komentarz": "JR",
    "kwota": "10.0",
    "data": "2026-04-24T22:49:35.067000+02:00"
  },
  {
    "osoba": "pozdro JR",
    "komentarz": "JR POZDROO MALOLATY",
    "kwota": "10.0",
    "data": "2026-04-25T22:22:05.156000+02:00"
  },
  {
    "osoba": "ArekBDG",
    "komentarz": "JR JR JR",
    "kwota": "10.0",
    "data": "2026-04-24T11:25:57.985000+02:00"
  },
  {
    "osoba": "Michał S",
    "komentarz": "JR",
    "kwota": "10.0",
    "data": "2026-04-26T19:08:47.851000+02:00"
  },
  {
    "osoba": "Natalia",
    "komentarz": "JR❤️‍🩹",
    "kwota": "10.0",
    "data": "2026-04-26T15:23:17.478000+02:00"
  },
  {
    "osoba": "Anonim",
    "komentarz": "Dacie radę !",
    "kwota": "10.0",
    "data": "2026-04-24T17:01:56.000000+02:00"
  },
  {
    "osoba": "Kim Jongseob",
    "komentarz": "Sigmowka reklamowka stan p1h",
    "kwota": "10.0",
    "data": "2026-04-25T22:58:41.404000+02:00"
  },
  {
    "osoba": "Monika",
    "komentarz": "Dla dzieci",
    "kwota": "10.0",
    "data": "2026-04-26T11:50:01.422000+02:00"
  },
  {
    "osoba": "Małgorzata Frajny",
    "komentarz": "Łysi rules",
    "kwota": "10.0",
    "data": "2026-04-26T14:03:38.895000+02:00"
  },
  {
    "osoba": "Maciej2012",
    "komentarz": "Super dziękuję, że mogłem pomóc.",
    "kwota": "10.0",
    "data": "2026-04-25T23:24:12.368000+02:00"
  },
  {
    "osoba": "Szymon Sz",
    "komentarz": "Pozdrawiam",
    "kwota": "10.0",
    "data": "2026-04-26T11:00:49.391000+02:00"
  },
  {
    "osoba": "Lilunia",
    "komentarz": "🩷🩷🩷",
    "kwota": "10.0",
    "data": "2026-04-26T14:39:40.514000+02:00"
  },
  {
    "osoba": "🫶🫶🫶🫶🫶🫶",
    "komentarz": "Julia i Bartek",
    "kwota": "10.0",
    "data": "2026-04-24T22:29:28.062000+02:00"
  },
  {
    "osoba": "Olek",
    "komentarz": "jesteśmy sigmami",
    "kwota": "10.0",
    "data": "2026-04-26T20:04:31.056000+02:00"
  },
  {
    "osoba": "Krzysztof.M.",
    "komentarz": "Dla małych wojowników!!💓",
    "kwota": "10.0",
    "data": "2026-04-23T18:11:18.621000+02:00"
  },
  {
    "osoba": "Anonim",
    "komentarz": "Rajder_",
    "kwota": "10.0",
    "data": "2026-04-25T21:59:06.089000+02:00"
  },
  {
    "osoba": "Damian Strzelecki",
    "komentarz": "Damy radę!!!",
    "kwota": "10.0",
    "data": "2026-04-25T18:53:41.281000+02:00"
  },
  {
    "osoba": "Przemyslaw",
    "komentarz": "JR",
    "kwota": "10.0",
    "data": "2026-04-26T16:07:29.771000+02:00"
  },
  {
    "osoba": "Anonim",
    "komentarz": "Dla wszystkich rodzin, w których zadomowił się ten rąk. JR",
    "kwota": "10.0",
    "data": "2026-04-25T17:11:23.677000+02:00"
  },
  {
    "osoba": "Andzia",
    "komentarz": "Pomagamy ❤️❤️",
    "kwota": "10.0",
    "data": "2026-04-26T12:50:18.318000+02:00"
  },
  {
    "osoba": "kubek",
    "komentarz": "JR",
    "kwota": "10.0",
    "data": "2026-04-23T21:53:14.478000+02:00"
  },
  {
    "osoba": "Wyszecka",
    "komentarz": "Powodzenia",
    "kwota": "10.0",
    "data": "2026-04-25T17:51:27.449000+02:00"
  },
  {
    "osoba": "Mart",
    "komentarz": "STOP LAAAT DŻASTA",
    "kwota": "10.0",
    "data": "2026-04-25T23:33:19.065000+02:00"
  },
  {
    "osoba": "meryska",
    "komentarz": "LECIMY",
    "kwota": "10.0",
    "data": "2026-04-26T01:15:38.785000+02:00"
  },
  {
    "osoba": "Marcin",
    "komentarz": "Brawo",
    "kwota": "10.0",
    "data": "2026-04-26T15:23:23.300000+02:00"
  },
  {
    "osoba": "Pati",
    "komentarz": "Genialne robota ❤️",
    "kwota": "10.0",
    "data": "2026-04-25T12:18:53.316000+02:00"
  },
  {
    "osoba": "Anonim",
    "komentarz": "JR",
    "kwota": "10.0",
    "data": "2026-04-25T20:05:46.569000+02:00"
  },
  {
    "osoba": "Tomasz",
    "komentarz": "Tak trzymać",
    "kwota": "10.0",
    "data": "2026-04-26T12:05:51.393000+02:00"
  },
  {
    "osoba": "skolim",
    "komentarz": "Temperaturaaaaaa",
    "kwota": "10.0",
    "data": "2026-04-25T17:26:19.348000+02:00"
  },
  {
    "osoba": "Miko",
    "komentarz": "JR!",
    "kwota": "10.0",
    "data": "2026-04-24T03:17:46.881000+02:00"
  },
  {
    "osoba": "nela",
    "komentarz": "❤️",
    "kwota": "10.0",
    "data": "2026-04-26T19:11:52.136000+02:00"
  },
  {
    "osoba": "Ania",
    "komentarz": "Piękna inicjatywa, wpłacam nie dużo, ale mam nadzieję, że pomogę 💪🫶",
    "kwota": "10.0",
    "data": "2026-04-26T13:31:28.102000+02:00"
  },
  {
    "osoba": "Zofia Rowek",
    "komentarz": "HEJ BRAWO WY",
    "kwota": "10.0",
    "data": "2026-04-26T18:02:14.071000+02:00"
  },
  {
    "osoba": "Sefko",
    "komentarz": "Jr",
    "kwota": "10.0",
    "data": "2026-04-25T18:30:46.819000+02:00"
  },
  {
    "osoba": "zosia",
    "komentarz": "JR 🔥🔥🔥",
    "kwota": "10.0",
    "data": "2026-04-25T20:59:50.742000+02:00"
  },
  {
    "osoba": "Ania",
    "komentarz": "Go go go !",
    "kwota": "10.0",
    "data": "2026-04-25T23:13:55.626000+02:00"
  },
  {
    "osoba": "Juby",
    "komentarz": "JRR",
    "kwota": "10.0",
    "data": "2026-04-25T23:47:39.126000+02:00"
  },
  {
    "osoba": "Anonim",
    "komentarz": "Pozdrowienia z Torunia",
    "kwota": "10.0",
    "data": "2026-04-26T17:21:39.333000+02:00"
  },
  {
    "osoba": "Hania",
    "komentarz": "Pozdrawiam wszystkich małych cudownych wojowników ❤️",
    "kwota": "10.0",
    "data": "2026-04-25T20:31:46.888000+02:00"
  },
  {
    "osoba": "Karolina",
    "komentarz": "❤️❤️❤️❤️❤️❤️",
    "kwota": "10.0",
    "data": "2026-04-24T20:53:38.908000+02:00"
  },
  {
    "osoba": "Kasia",
    "komentarz": "Lets gooo🔥🔥",
    "kwota": "10.0",
    "data": "2026-04-26T13:50:12.333000+02:00"
  },
  {
    "osoba": "pati",
    "komentarz": "dobra robota!",
    "kwota": "10.0",
    "data": "2026-04-25T22:14:10.509000+02:00"
  },
  {
    "osoba": "Maksymilian i Babcia",
    "komentarz": "Namówiłem moją babcie",
    "kwota": "10.0",
    "data": "2026-04-26T19:25:43.283000+02:00"
  },
  {
    "osoba": "Foczka",
    "komentarz": "NAWETZLOTÓWKASIELICZY",
    "kwota": "10.0",
    "data": "2026-04-26T21:35:06.466000+02:00"
  },
  {
    "osoba": "gargamel",
    "komentarz": "mini majk na gargamela",
    "kwota": "10.0",
    "data": "2026-04-25T23:09:49.214000+02:00"
  },
  {
    "osoba": "Oskar i Dominka",
    "komentarz": "<3",
    "kwota": "10.0",
    "data": "2026-04-23T18:56:58.090000+02:00"
  },
  {
    "osoba": "Wojciech Cygiel",
    "komentarz": "❤️",
    "kwota": "10.0",
    "data": "2026-04-26T17:01:00.693000+02:00"
  },
  {
    "osoba": "Tadeusz *****ździsko",
    "komentarz": "Pozdro wariaty",
    "kwota": "10.0",
    "data": "2026-04-24T19:13:03.834000+02:00"
  },
  {
    "osoba": "sanderka",
    "komentarz": "super!!!!!",
    "kwota": "10.0",
    "data": "2026-04-25T21:31:39.916000+02:00"
  },
  {
    "osoba": "Kajo",
    "komentarz": "Lecisz dalej sztywno🫡",
    "kwota": "10.0",
    "data": "2026-04-25T20:09:31.123000+02:00"
  },
  {
    "osoba": "Patrysia",
    "komentarz": "Super akcja",
    "kwota": "10.0",
    "data": "2026-04-26T11:38:46.602000+02:00"
  },
  {
    "osoba": "Kubuś",
    "komentarz": "Lecimy!!",
    "kwota": "10.0",
    "data": "2026-04-24T10:16:27.493000+02:00"
  },
  {
    "osoba": "Mikołaj",
    "komentarz": "🫶🏻🫶🏻🫶🏻",
    "kwota": "10.0",
    "data": "2026-04-26T09:43:45.602000+02:00"
  },
  {
    "osoba": "Kocham Artura",
    "komentarz": "Kocham was",
    "kwota": "10.0",
    "data": "2026-04-25T22:18:55.825000+02:00"
  },
  {
    "osoba": "Ania",
    "komentarz": "Jesteście wielcy !!!",
    "kwota": "7.0",
    "data": "2026-04-25T18:13:26.702000+02:00"
  },
  {
    "osoba": "kajtek bez majtek",
    "komentarz": "jestem gejem",
    "kwota": "6.7",
    "data": "2026-04-26T11:14:07.288000+02:00"
  },
  {
    "osoba": "Nyna",
    "komentarz": "Robimyyy",
    "kwota": "5.5",
    "data": "2026-04-26T21:30:55.927000+02:00"
  },
  {
    "osoba": "Nikola",
    "komentarz": "<3",
    "kwota": "5.0",
    "data": "2026-04-26T15:57:07.058000+02:00"
  },
  {
    "osoba": "Majolcia",
    "komentarz": "Pozdro",
    "kwota": "5.0",
    "data": "2026-04-26T20:23:24.464000+02:00"
  },
  {
    "osoba": "N",
    "komentarz": "Let’s go!!!",
    "kwota": "5.0",
    "data": "2026-04-26T15:49:27.708000+02:00"
  },
  {
    "osoba": "Alicja",
    "komentarz": "jesteście wielcy",
    "kwota": "5.0",
    "data": "2026-04-25T01:28:48.916000+02:00"
  },
  {
    "osoba": "pomagamy i pozdro bedi",
    "komentarz": "Pomagamy🥰  pozdrawiamy",
    "kwota": "5.0",
    "data": "2026-04-26T17:45:52.916000+02:00"
  },
  {
    "osoba": "Kołek",
    "komentarz": "Polska górą",
    "kwota": "5.0",
    "data": "2026-04-26T16:10:05.060000+02:00"
  },
  {
    "osoba": "JAJO",
    "komentarz": "pozdro",
    "kwota": "5.0",
    "data": "2026-04-24T19:40:03.098000+02:00"
  },
  {
    "osoba": "Marta",
    "komentarz": "lecimy",
    "kwota": "5.0",
    "data": "2026-04-26T21:36:57.875000+02:00"
  },
  {
    "osoba": "Oliwka Kornela Martyna Ola",
    "komentarz": "POMAGAJMY",
    "kwota": "5.0",
    "data": "2026-04-26T14:13:14.835000+02:00"
  },
  {
    "osoba": "zuzia❤️❤️",
    "komentarz": "JR",
    "kwota": "5.0",
    "data": "2026-04-26T19:15:26.415000+02:00"
  },
  {
    "osoba": "piwniczanka",
    "komentarz": "JR",
    "kwota": "5.0",
    "data": "2026-04-23T21:54:45.918000+02:00"
  },
  {
    "osoba": "Jakub",
    "komentarz": "Pomagamy",
    "kwota": "5.0",
    "data": "2026-04-24T13:11:51.202000+02:00"
  },
  {
    "osoba": "Kris",
    "komentarz": "Tak trzymać",
    "kwota": "5.0",
    "data": "2026-04-26T20:46:51.152000+02:00"
  },
  {
    "osoba": "Teodor",
    "komentarz": "Trzymamy łapki 🩷",
    "kwota": "5.0",
    "data": "2026-04-23T12:45:34.521000+02:00"
  },
  {
    "osoba": "Amelka i Lila",
    "komentarz": "Serdecznie Pozdrawiamy",
    "kwota": "5.0",
    "data": "2026-04-25T21:42:41.567000+02:00"
  },
  {
    "osoba": "Bosmann pomaga",
    "komentarz": "Jesteście wielcy",
    "kwota": "5.0",
    "data": "2026-04-26T19:42:51.508000+02:00"
  },
  {
    "osoba": "Pozdrawiam",
    "komentarz": "Każdy grosz się liczy",
    "kwota": "5.0",
    "data": "2026-04-26T08:48:50.506000+02:00"
  },
  {
    "osoba": "Martyna",
    "komentarz": "❤️",
    "kwota": "5.0",
    "data": "2026-04-26T21:01:31.589000+02:00"
  },
  {
    "osoba": "Xdrko8💗",
    "komentarz": "Świetne jest co to robiciee",
    "kwota": "5.0",
    "data": "2026-04-26T19:32:33.853000+02:00"
  },
  {
    "osoba": "Anonim",
    "komentarz": "Głowa do góry",
    "kwota": "5.0",
    "data": "2026-04-26T09:32:39.168000+02:00"
  },
  {
    "osoba": "Ewelina",
    "komentarz": "JEDZIEMY!!!",
    "kwota": "5.0",
    "data": "2026-04-25T12:10:48.817000+02:00"
  },
  {
    "osoba": "Melka",
    "komentarz": "Gratulacje dla kazdego!!!",
    "kwota": "5.0",
    "data": "2026-04-26T13:23:01.039000+02:00"
  },
  {
    "osoba": "Anonim",
    "komentarz": "JR",
    "kwota": "5.0",
    "data": "2026-04-26T21:21:14.853000+02:00"
  },
  {
    "osoba": "Kóba i Tata",
    "komentarz": "Wspaniała Akcja",
    "kwota": "5.0",
    "data": "2026-04-26T13:00:12.321000+02:00"
  },
  {
    "osoba": "Olaaaa",
    "komentarz": "buziaki poznań <3",
    "kwota": "5.0",
    "data": "2026-04-24T14:37:01.964000+02:00"
  },
  {
    "osoba": "Anonim",
    "komentarz": "Dacie radę ❤",
    "kwota": "5.0",
    "data": "2026-04-25T12:05:09.974000+02:00"
  },
  {
    "osoba": "Blanka",
    "komentarz": "❤️❤️❤️",
    "kwota": "5.0",
    "data": "2026-04-23T21:30:30.676000+02:00"
  },
  {
    "osoba": "Lena",
    "komentarz": "Pozdrooo",
    "kwota": "5.0",
    "data": "2026-04-26T17:49:42.838000+02:00"
  },
  {
    "osoba": "Jedziemy po 100ml",
    "komentarz": "Piotrek jesteś wielki",
    "kwota": "5.0",
    "data": "2026-04-26T11:15:37.911000+02:00"
  },
  {
    "osoba": "Norbert",
    "komentarz": "jr",
    "kwota": "5.0",
    "data": "2026-04-26T20:44:34.757000+02:00"
  },
  {
    "osoba": "Mati",
    "komentarz": "Pozdro",
    "kwota": "5.0",
    "data": "2026-04-24T22:26:40.791000+02:00"
  },
  {
    "osoba": "Anonim",
    "komentarz": "❤️",
    "kwota": "5.0",
    "data": "2026-04-26T08:08:02.549000+02:00"
  },
  {
    "osoba": "ssupmiluss",
    "komentarz": "💕💕",
    "kwota": "5.0",
    "data": "2026-04-26T00:19:37.954000+02:00"
  },
  {
    "osoba": "Fiksiu",
    "komentarz": "❤️❤️❤️❤️❤️",
    "kwota": "5.0",
    "data": "2026-04-25T20:51:36.624000+02:00"
  },
  {
    "osoba": "Patka B.",
    "komentarz": "Pomagamy ❤️",
    "kwota": "5.0",
    "data": "2026-04-24T13:12:53.018000+02:00"
  },
  {
    "osoba": "Karlosza",
    "komentarz": "Xd",
    "kwota": "5.0",
    "data": "2026-04-26T00:16:08.479000+02:00"
  },
  {
    "osoba": "Kuba1908",
    "komentarz": "JR",
    "kwota": "4.0",
    "data": "2026-04-26T20:34:05.636000+02:00"
  },
  {
    "osoba": "neqq",
    "komentarz": "zdrowia",
    "kwota": "3.0",
    "data": "2026-04-26T17:48:19.359000+02:00"
  },
  {
    "osoba": "zuk",
    "komentarz": "pozdrawiam jacob and fylop",
    "kwota": "3.0",
    "data": "2026-04-25T17:42:46.412000+02:00"
  },
  {
    "osoba": "Wizjoner",
    "komentarz": "Zdrówka",
    "kwota": "3.0",
    "data": "2026-04-25T22:42:55.043000+02:00"
  },
  {
    "osoba": "Julka",
    "komentarz": "Trzymajcie się dzieciaki i walczcie dalej ❤️",
    "kwota": "3.0",
    "data": "2026-04-26T14:31:46.581000+02:00"
  },
  {
    "osoba": "Anonim",
    "komentarz": "Pozdro łatwo",
    "kwota": "3.0",
    "data": "2026-04-26T12:36:12.711000+02:00"
  },
  {
    "osoba": "Hubert",
    "komentarz": "<3",
    "kwota": "3.0",
    "data": "2026-04-26T14:20:12.886000+02:00"
  },
  {
    "osoba": "Szczypek",
    "komentarz": "Kocham stopy",
    "kwota": "2.5",
    "data": "2026-04-26T18:21:23.260000+02:00"
  },
  {
    "osoba": "Klaudiaaaaaaaaaaa",
    "komentarz": "!!!!!!",
    "kwota": "2.1",
    "data": "2026-04-26T21:35:20.283000+02:00"
  },
  {
    "osoba": "Anonim",
    "komentarz": "Pozdro",
    "kwota": "2.0",
    "data": "2026-04-26T12:40:52.070000+02:00"
  },
  {
    "osoba": "Sandra",
    "komentarz": "DAMY RADEE!! ❤️‍🩹❤️‍🩹",
    "kwota": "2.0",
    "data": "2026-04-26T20:28:57.917000+02:00"
  },
  {
    "osoba": "Anonim",
    "komentarz": "❤️❤️",
    "kwota": "2.0",
    "data": "2026-04-24T15:26:50.312000+02:00"
  },
  {
    "osoba": "Przemek",
    "komentarz": "Pomoc jest najważniejsza",
    "kwota": "2.0",
    "data": "2026-04-26T01:41:38.902000+02:00"
  },
  {
    "osoba": "Skrzat",
    "komentarz": "JR!!! <3",
    "kwota": "1.0",
    "data": "2026-04-26T19:39:04.608000+02:00"
  },
  {
    "osoba": "Majaa",
    "komentarz": "Jr!!",
    "kwota": "1.0",
    "data": "2026-04-26T20:19:26.654000+02:00"
  },
  {
    "osoba": "DzuliaJ",
    "komentarz": "kocham Mateusz  Brzezno",
    "kwota": "1.0",
    "data": "2026-04-26T18:04:26.386000+02:00"
  },
  {
    "osoba": "GIBEKKK",
    "komentarz": "POZDROOO!",
    "kwota": "1.0",
    "data": "2026-04-26T15:35:19.436000+02:00"
  },
  {
    "osoba": "Kaja",
    "komentarz": "🩷🩷 Gratulacje",
    "kwota": null,
    "data": "2026-04-26T16:41:22.704000+02:00"
  },
  {
    "osoba": "Anonim",
    "komentarz": "JR",
    "kwota": null,
    "data": "2026-04-26T21:39:02.159000+02:00"
  },
  {
    "osoba": "Dorota",
    "komentarz": "🤘",
    "kwota": null,
    "data": "2026-04-25T21:15:39.106000+02:00"
  },
  {
    "osoba": "Anonim",
    "komentarz": "Przepraszam, że tak mało ale to wszystko co mam. Dedykuję to mojej zmarłej przyjaciółce",
    "kwota": null,
    "data": "2026-04-26T21:53:31.303000+02:00"
  },
  {
    "osoba": "Rafał Baranowski",
    "komentarz": "Dobro wraca",
    "kwota": null,
    "data": "2026-04-26T13:20:41.892000+02:00"
  },
  {
    "osoba": "Robert i Wera",
    "komentarz": "❤️",
    "kwota": null,
    "data": "2026-04-25T20:43:08.930000+02:00"
  },
  {
    "osoba": "julka",
    "komentarz": "dacie radę!",
    "kwota": null,
    "data": "2026-04-26T00:00:27.586000+02:00"
  },
  {
    "osoba": "Joanna",
    "komentarz": "Go!",
    "kwota": null,
    "data": "2026-04-26T10:59:57.743000+02:00"
  },
  {
    "osoba": "Madzia",
    "komentarz": "💓",
    "kwota": null,
    "data": "2026-04-26T20:25:26.100000+02:00"
  },
  {
    "osoba": "Anonim",
    "komentarz": "traczu",
    "kwota": null,
    "data": "2026-04-26T13:30:47.586000+02:00"
  },
  {
    "osoba": "Kamil",
    "komentarz": "Lecimy dalej 🙂",
    "kwota": null,
    "data": "2026-04-25T20:14:07.854000+02:00"
  },
  {
    "osoba": "Asia i Rafał",
    "komentarz": "❤️",
    "kwota": null,
    "data": "2026-04-25T23:17:25.991000+02:00"
  },
  {
    "osoba": "Emilos",
    "komentarz": "Powodzenia!!",
    "kwota": null,
    "data": "2026-04-26T20:05:07.323000+02:00"
  },
  {
    "osoba": "Kasiaaaaaaaaaaa P",
    "komentarz": "Piękna akcja",
    "kwota": null,
    "data": "2026-04-26T20:22:22.165000+02:00"
  },
  {
    "osoba": "Daria",
    "komentarz": "🔥🔥🔥",
    "kwota": null,
    "data": "2026-04-26T20:26:26.737000+02:00"
  },
  {
    "osoba": "Anonim",
    "komentarz": "Tak trzymajcie! ❤️❤️❤️",
    "kwota": null,
    "data": "2026-04-25T18:39:52.208000+02:00"
  },
  {
    "osoba": "karol wojtyla",
    "komentarz": "🥰❤️🌹🐻",
    "kwota": null,
    "data": "2026-04-26T12:10:16.321000+02:00"
  },
  {
    "osoba": "Dominika i Radek",
    "komentarz": "Jesteście wspaniali!!!",
    "kwota": null,
    "data": "2026-04-26T13:57:25.307000+02:00"
  },
  {
    "osoba": "Minnie_Official z tikotoka",
    "komentarz": "Jesteście wielcy ❤️❤️ dla dzieci zawsze będę pomagać",
    "kwota": null,
    "data": "2026-04-26T19:12:08.261000+02:00"
  },
  {
    "osoba": "Anonim",
    "komentarz": "Pomagamy",
    "kwota": null,
    "data": "2026-04-26T12:47:33.169000+02:00"
  },
  {
    "osoba": "Anonim",
    "komentarz": "Walczycie dzi",
    "kwota": null,
    "data": "2026-04-26T09:25:50.469000+02:00"
  },
  {
    "osoba": "Anitka111999",
    "komentarz": "❤️‍🩹",
    "kwota": null,
    "data": "2026-04-26T12:15:59.926000+02:00"
  },
  {
    "osoba": "Anonim",
    "komentarz": "🥰",
    "kwota": null,
    "data": "2026-04-26T17:04:05.129000+02:00"
  },
  {
    "osoba": "Anonim",
    "komentarz": "Walczymy",
    "kwota": null,
    "data": "2026-04-24T11:47:16.301000+02:00"
  },
  {
    "osoba": "GRAMY",
    "komentarz": "GRAMY z Cancer Fighters",
    "kwota": null,
    "data": "2026-04-26T16:54:52.777000+02:00"
  },
  {
    "osoba": "Szymon",
    "komentarz": "❤️❤️",
    "kwota": null,
    "data": "2026-04-26T20:59:13.448000+02:00"
  }
]